Lab4_FSM/mealy-type-vending-machine/RTL/vending_machine_mealy.v
`timescale 1ns/1ps

module vending_machine_mealy (
    input wire clk,
    input wire rstn,
    input wire [1:0] coin,

    output wire [1:0] change,
    output wire sell
);

// machine state decode
parameter IDLE = 2'd0,
          GET05 = 2'd1,
          GET10 = 2'd2,
          GET15 = 2'd3;

// machine variable
reg [1:0] st_next;
reg [1:0] st_cur;

// define how to transfer the state
always @(posedge clk or negedge rstn) begin
    if(!rstn) begin
        st_cur <= IDLE;
    end
    else begin
        st_cur <= st_next;
    end
end

// define how to determine the next state
always @(*) begin
    case(st_cur)
        IDLE: 
            case(coin)
                2'd1: st_next = GET05;
                2'd2: st_next = GET10;
                default: st_next = IDLE;
            endcase
        GET05:
            case(coin)
                2'd1: st_next = GET10;
                2'd2: st_next = GET15;
                default: st_next = GET05;
            endcase
        GET10:
            case(coin)
                2'd1: st_next = GET15;
                2'd2: st_next = IDLE;
                default: st_next = GET10;
            endcase
        GET15:
            case(coin)
                2'd1: st_next = IDLE;
                2'd2: st_next = IDLE;
                default: st_next = GET15;
            endcase
        default:
            st_next = IDLE;
    endcase
end

// define how to generate outputs
reg [1:0] change_r;
reg sell_r;

always @(posedge clk or negedge rstn) begin
    if (!rstn) begin
        change_r <= 2'd0;
        sell_r <= 1'd0;
    end
    else if ((st_cur == GET15 && coin == 2'd1) ||
             (st_cur == GET10 && coin == 2'd2)) begin
        change_r <= 2'd0;
        sell_r <= 1'd1;
    end
    else if ((st_cur == GET15 && coin == 2'd2)) begin
        change_r <= 2'd1;
        sell_r <= 1'd1;
    end
    else begin
        change_r <= 2'd0;
        sell_r <= 1'd0;
    end
end

assign sell = sell_r;
assign change = change_r;
    
endmodule

Lab4_FSM/mealy-type-vending-machine/sim-wave/tb_vending_machine_mealy.v
`timescale 1ns/1ps

module tb_vending_machine_mealy();

// Declare artificial input signal
reg artificial_clk;
reg artificial_rstn;
reg [1:0] artificial_coin;
// Declare output record signal
wire [1:0] change_record;
wire sell_record;

// Define waveform record file
initial begin
    $dumpfile("signals_tb_vending_machine_mealy.vcd");
    $dumpvars(0, tb_vending_machine_mealy);
end

// Define stop time
initial begin
    #10000
    $finish;
end

// Generate artificial inputs
// Define the initial value of the artificial inputs
 initial begin
	 artificial_clk = 1'b1;
	 artificial_rstn <= 1'b0;
     artificial_coin <= 2'b0;
	 #200
	 artificial_rstn <= 1'b1;
 end
//Generate system clock, 50MHz
 always #10 artificial_clk = ~artificial_clk ;
 // Every 500 ns, generate a random number. This random number will 
// take the modulus and find the remainder to generate random 0, 1, 2 
always begin
    #500 artificial_coin <= ($urandom) % 3;
    #20 artificial_coin <= 1'b0;
end

// instance
vending_machine_mealy vending_machine_mealy_inst
(
    .clk(artificial_clk),
    .rstn(artificial_rstn),
    .coin(artificial_coin),

    .change(change_record),
    .sell(sell_record)
);

endmodule

Lab4_FSM/mealy-type-vending-machine/sim-wave/signals_tb_vending_machine_mealy.vcd
$date
	Wed Oct 15 13:55:53 2025
$end
$version
	Icarus Verilog
$end
$timescale
	1ps
$end
$scope module tb_vending_machine_mealy $end
$var wire 1 ! sell_record $end
$var wire 2 " change_record [1:0] $end
$var reg 1 # artificial_clk $end
$var reg 2 $ artificial_coin [1:0] $end
$var reg 1 % artificial_rstn $end
$scope module vending_machine_mealy_inst $end
$var wire 2 & change [1:0] $end
$var wire 1 # clk $end
$var wire 2 ' coin [1:0] $end
$var wire 1 % rstn $end
$var wire 1 ! sell $end
$var reg 2 ( change_r [1:0] $end
$var reg 1 ) sell_r $end
$var reg 2 * st_cur [1:0] $end
$var reg 2 + st_next [1:0] $end
$upscope $end
$upscope $end
$enddefinitions $end
#0
$dumpvars
b0 +
b0 *
0)
b0 (
b0 '
b0 &
0%
b0 $
1#
b0 "
0!
$end
#10000
0#
#20000
1#
#30000
0#
#40000
1#
#50000
0#
#60000
1#
#70000
0#
#80000
1#
#90000
0#
#100000
1#
#110000
0#
#120000
1#
#130000
0#
#140000
1#
#150000
0#
#160000
1#
#170000
0#
#180000
1#
#190000
0#
#200000
1%
1#
#210000
0#
#220000
1#
#230000
0#
#240000
1#
#250000
0#
#260000
1#
#270000
0#
#280000
1#
#290000
0#
#300000
1#
#310000
0#
#320000
1#
#330000
0#
#340000
1#
#350000
0#
#360000
1#
#370000
0#
#380000
1#
#390000
0#
#400000
1#
#410000
0#
#420000
1#
#430000
0#
#440000
1#
#450000
0#
#460000
1#
#470000
0#
#480000
1#
#490000
0#
#500000
b1 +
b1 $
b1 '
1#
#510000
0#
#520000
b1 *
b0 $
b0 '
1#
#530000
0#
#540000
1#
#550000
0#
#560000
1#
#570000
0#
#580000
1#
#590000
0#
#600000
1#
#610000
0#
#620000
1#
#630000
0#
#640000
1#
#650000
0#
#660000
1#
#670000
0#
#680000
1#
#690000
0#
#700000
1#
#710000
0#
#720000
1#
#730000
0#
#740000
1#
#750000
0#
#760000
1#
#770000
0#
#780000
1#
#790000
0#
#800000
1#
#810000
0#
#820000
1#
#830000
0#
#840000
1#
#850000
0#
#860000
1#
#870000
0#
#880000
1#
#890000
0#
#900000
1#
#910000
0#
#920000
1#
#930000
0#
#940000
1#
#950000
0#
#960000
1#
#970000
0#
#980000
1#
#990000
0#
#1000000
1#
#1010000
0#
#1020000
b10 +
b1 $
b1 '
1#
#1030000
0#
#1040000
b10 *
b0 $
b0 '
1#
#1050000
0#
#1060000
1#
#1070000
0#
#1080000
1#
#1090000
0#
#1100000
1#
#1110000
0#
#1120000
1#
#1130000
0#
#1140000
1#
#1150000
0#
#1160000
1#
#1170000
0#
#1180000
1#
#1190000
0#
#1200000
1#
#1210000
0#
#1220000
1#
#1230000
0#
#1240000
1#
#1250000
0#
#1260000
1#
#1270000
0#
#1280000
1#
#1290000
0#
#1300000
1#
#1310000
0#
#1320000
1#
#1330000
0#
#1340000
1#
#1350000
0#
#1360000
1#
#1370000
0#
#1380000
1#
#1390000
0#
#1400000
1#
#1410000
0#
#1420000
1#
#1430000
0#
#1440000
1#
#1450000
0#
#1460000
1#
#1470000
0#
#1480000
1#
#1490000
0#
#1500000
1#
#1510000
0#
#1520000
1#
#1530000
0#
#1540000
b0 +
b10 $
b10 '
1#
#1550000
0#
#1560000
1!
1)
b0 *
b0 $
b0 '
1#
#1570000
0#
#1580000
0!
0)
1#
