Lab1/RTL/led.v
`timescale 1ns/1ps

module led (
    input wire key_in,
    output wire led_out
);

assign led_out = key_in;
    
endmodule

Lab1/sim/tb_led.v
`timescale 1ns/1ps

module tb_led();

// Declare artificial input signal
reg artificial_key_in;
// Declare output record signal
wire record_led_out;

// Define stop time
initial begin
    #10000 $finish;
end

// Define waveform record file
initial begin
    $dumpfile("signals_tb_led.vcd");
    $dumpvars(0, tb_led);
end

// Generate artificial inputs
// Define the initial value of the artificial inputs
initial begin
    artificial_key_in <= 1'b0;
end
// Every 10 ns, generate a random number. This random number will 
// take the modulus and find the remainder to generate random 0 and 1 
always begin
    #10 artificial_key_in <= ($random) % 2;
end

// Instantiate the module that is tested
led led_inst(
    .key_in(artificial_key_in),
    .led_out(record_led_out)
);

endmodule

Lab1/sim-wave/signals_tb_led.vcd
$date
	Tue Oct 14 20:51:45 2025
$end
$version
	Icarus Verilog
$end
$timescale
	1ps
$end
$scope module tb_led $end
$var wire 1 ! record_led_out $end
$var reg 1 " artificial_key_in $end
$scope module led_inst $end
$var wire 1 " key_in $end
$var wire 1 ! led_out $end
$upscope $end
$upscope $end
$enddefinitions $end
$comment Show the parameter values. $end
$dumpall
$end
#0
$dumpvars
0"
0!
$end
#20000
1!
1"
#80000
0!
0"
#90000
1!
1"
#110000
0!
0"
#120000
1!
1"
#140000
0!
0"
#150000
1!
1"
#160000
0!
0"
#170000
1!
1"
#180000
0!
0"
#190000
1!
1"
#210000
0!
0"
#220000
1!
1"
#230000
0!
0"
#260000
1!
1"
#270000
0!
0"
#280000
1!
1"
#320000
0!
0"
#360000
1!
1"
#370000
0!
0"
#380000
1!
1"
#430000
0!
0"
#450000
1!
1"
#480000
0!
0"
#530000
1!
1"
#540000
0!
0"
#560000
1!
1"
#580000
0!
0"
#630000
1!
1"
#680000
0!
0"
#700000
1!
1"
#730000
0!
0"
#750000
1!
1"
#770000
0!
0"
#780000
1!
1"
#800000
0!
0"
#810000
1!
1"
#840000
0!
0"
#850000
1!
1"
#870000
0!
0"
#910000
1!
1"
#930000
0!
0"
#950000
1!
1"
#1000000
0!
0"
#1010000
1!
1"
#1040000
0!
0"
#1110000
1!
1"
#1160000
0!
0"
#1170000
1!
1"
#1190000
0!
0"
#1210000
1!
1"
#1230000
0!
0"
#1240000
1!
1"
#1280000
0!
0"
#1310000
1!
1"
#1320000
0!
0"
#1350000
1!
1"
#1370000
0!
0"
#1390000
1!
1"
#1400000
0!
0"
#1430000
1!
1"
#1440000
0!
0"
#1460000
1!
1"
#1470000
0!
0"
#1480000
1!
1"
#1530000
0!
0"
#1560000
1!
1"
#1570000
0!
0"
#1590000
1!
1"
#1610000
0!
0"
#1640000
1!
1"
#1660000
0!
0"
#1690000
1!
1"
#1710000
0!
0"
#1740000
1!
1"
#1750000
0!
0"
#1770000
1!
1"
#1780000
0!
0"
#1810000
1!
1"
#1820000
0!
0"
#1830000
1!
1"
#1850000
0!
0"
#1890000
1!
1"
#1900000
0!
0"
#1940000
1!
1"
#1970000
0!
0"
#1980000
1!
1"
#2010000
0!
0"
#2030000
1!
1"
#2080000
0!
0"
#2090000
1!
1"
#2110000
0!
0"
#2150000
1!
1"
#2170000
0!
0"
#2190000
1!
1"
#2200000
0!
0"
#2220000
1!
1"
#2230000
0!
0"
#2250000
1!
1"
#2260000
0!
0"
#2280000
1!
1"
#2310000
0!
0"
#2340000
1!
1"
#2350000
0!
0"
#2370000
1!
1"
#2380000
0!
0"
#2420000
1!
1"
#2430000
0!
0"
#2460000
1!
1"
#2480000
0!
0"
#2490000
1!
1"
#2530000
0!
0"
#2540000
1!
1"
#2570000
0!
0"
#2590000
1!
1"
#2600000
0!
0"
#2620000
1!
1"
#2640000
0!
0"
#2660000
1!
1"
#2670000
0!
0"
#2690000
1!
1"
#2700000
0!
0"
#2710000
1!
1"
#2730000
0!
0"
#2740000
1!
1"
#2750000
0!
0"
#2760000
1!
1"
#2770000
0!
0"
#2790000
1!
1"
#2800000
0!
0"
#2830000
1!
1"
#2880000
0!
0"
#2890000
1!
1"
#2920000
0!
0"
#2980000
1!
1"
#3050000
0!
0"
#3060000
1!
1"
#3140000
0!
0"
#3160000
1!
1"
#3180000
0!
0"
#3220000
1!
1"
#3230000
0!
0"
#3290000
1!
1"
#3300000
0!
0"
#3320000
1!
1"
#3330000
0!
0"
#3370000
1!
1"
#3420000
0!
0"
#3430000
1!
1"
#3460000
0!
0"
#3470000
1!
1"
#3480000
0!
0"
#3500000
1!
1"
#3520000
0!
0"
#3530000
1!
1"
#3540000
0!
0"
#3560000
1!
1"
#3570000
0!
0"
#3610000
1!
1"
#3650000
0!
0"
#3660000
1!
1"
#3730000
0!
0"
#3740000
1!
1"
#3750000
0!
0"
#3760000
1!
1"
#3770000
0!
0"
#3790000
1!
1"
#3800000
0!
0"
#3850000
1!
1"
#3860000
0!
0"
#3920000
1!
1"
#3930000
0!
0"
#3940000
1!
1"
#3950000
0!
0"
#3970000
1!
1"
#3980000
0!
0"
#3990000
1!
1"
#4010000
0!
0"
#4020000
1!
1"
#4030000
0!
0"
#4040000
1!
1"
#4050000
0!
0"
#4090000
1!
1"
#4100000
0!
0"
#4110000
1!
1"
#4120000
0!
0"
#4130000
1!
1"
#4150000
0!
0"
#4160000
1!
1"
#4170000
0!
0"
#4180000
1!
1"
#4210000
0!
0"
#4220000
1!
1"
#4240000
0!
0"
#4260000
1!
1"
#4280000
0!
0"
#4300000
1!
1"
#4320000
0!
0"
#4340000
1!
1"
#4350000
0!
0"
#4370000
1!
1"
#4390000
0!
0"
#4410000
1!
1"
#4420000
0!
0"
#4440000
1!
1"
#4460000
0!
0"
#4470000
1!
1"
#4480000
0!
0"
#4490000
1!
1"
#4510000
0!
0"
#4520000
1!
1"
#4550000
0!
0"
#4560000
1!
1"
#4590000
0!
0"
#4610000
1!
1"
#4620000
0!
0"
#4640000
1!
1"
#4650000
0!
0"
#4670000
1!
1"
#4690000
0!
0"
#4700000
1!
1"
#4710000
0!
0"
#4720000
1!
1"
#4760000
0!
0"
#4780000
1!
1"
#4790000
0!
0"
#4800000
1!
1"
#4810000
0!
0"
#4820000
1!
1"
#4840000
0!
0"
#4860000
1!
1"
#4890000
0!
0"
#4910000
1!
1"
#4920000
0!
0"
#4940000
1!
1"
#4970000
0!
0"
#4980000
1!
1"
#5000000
0!
0"
#5030000
1!
1"
#5060000
0!
0"
#5090000
1!
1"
#5130000
0!
0"
#5140000
1!
1"
#5210000
0!
0"
#5220000
1!
1"
#5230000
0!
0"
#5260000
1!
1"
#5350000
0!
0"
#5380000
1!
1"
#5390000
0!
0"
#5420000
1!
1"
#5440000
0!
0"
#5470000
1!
1"
#5490000
0!
0"
#5500000
1!
1"
#5510000
0!
0"
#5520000
1!
1"
#5530000
0!
0"
#5560000
1!
1"
#5590000
0!
0"
#5600000
1!
1"
#5610000
0!
0"
#5620000
1!
1"
#5630000
0!
0"
#5640000
1!
1"
#5660000
0!
0"
#5700000
1!
1"
#5720000
0!
0"
#5740000
1!
1"
#5750000
0!
0"
#5760000
1!
1"
#5770000
0!
0"
#5780000
1!
1"
#5800000
0!
0"
#5810000
1!
1"
#5830000
0!
0"
#5870000
1!
1"
#5920000
0!
0"
#5990000
1!
1"
#6060000
0!
0"
#6120000
1!
1"
#6140000
0!
0"
#6150000
1!
1"
#6160000
0!
0"
#6170000
1!
1"
#6200000
0!
0"
#6230000
1!
1"
#6250000
0!
0"
#6260000
1!
1"
#6270000
0!
0"
#6330000
1!
1"
#6340000
0!
0"
#6360000
1!
1"
#6370000
0!
0"
#6390000
1!
1"
#6420000
0!
0"
#6440000
1!
1"
#6480000
0!
0"
#6490000
1!
1"
#6530000
0!
0"
#6540000
1!
1"
#6550000
0!
0"
#6570000
1!
1"
#6580000
0!
0"
#6600000
1!
1"
#6610000
0!
0"
#6670000
1!
1"
#6690000
0!
0"
#6710000
1!
1"
#6780000
0!
0"
#6790000
1!
1"
#6800000
0!
0"
#6830000
1!
1"
#6850000
0!
0"
#6860000
1!
1"
#6890000
0!
0"
#6930000
1!
1"
#6960000
0!
0"
#6970000
1!
1"
#6980000
0!
0"
#7050000
1!
1"
#7060000
0!
0"
#7080000
1!
1"
#7130000
0!
0"
#7170000
1!
1"
#7190000
0!
0"
#7210000
1!
1"
#7260000
0!
0"
#7290000
1!
1"
#7300000
0!
0"
#7310000
1!
1"
#7320000
0!
0"
#7370000
1!
1"
#7380000
0!
0"
#7390000
1!
1"
#7410000
0!
0"
#7420000
1!
1"
#7440000
0!
0"
#7450000
1!
1"
#7460000
0!
0"
#7470000
1!
1"
#7490000
0!
0"
#7510000
1!
1"
#7530000
0!
0"
#7570000
1!
1"
#7600000
0!
0"
#7620000
1!
1"
#7660000
0!
0"
#7680000
1!
1"
#7700000
0!
0"
#7720000
1!
1"
#7730000
0!
0"
#7740000
1!
1"
#7750000
0!
0"
#7760000
1!
1"
#7780000
0!
0"
#7830000
1!
1"
#7840000
0!
0"
#7850000
1!
1"
#7860000
0!
0"
#7890000
1!
1"
#7900000
0!
0"
#7920000
1!
1"
#7930000
0!
0"
#7940000
1!
1"
#7990000
0!
0"
#8000000
1!
1"
#8020000
0!
0"
#8040000
1!
1"
#8050000
0!
0"
#8060000
1!
1"
#8110000
0!
0"
#8120000
1!
1"
#8130000
0!
0"
#8140000
1!
1"
#8150000
0!
0"
#8160000
1!
1"
#8180000
0!
0"
#8220000
1!
1"
#8240000
0!
0"
#8260000
1!
1"
#8310000
0!
0"
#8350000
1!
1"
#8360000
0!
0"
#8380000
1!
1"
#8390000
0!
0"
#8400000
1!
1"
#8410000
0!
0"
#8430000
1!
1"
#8440000
0!
0"
#8480000
1!
1"
#8490000
0!
0"
#8500000
1!
1"
#8520000
0!
0"
#8540000
1!
1"
#8550000
0!
0"
#8560000
1!
1"
#8600000
0!
0"
#8610000
1!
1"
#8620000
0!
0"
#8640000
1!
1"
#8670000
0!
0"
#8680000
1!
1"
#8740000
0!
0"
#8750000
1!
1"
#8760000
0!
0"
#8790000
1!
1"
#8800000
0!
0"
#8810000
1!
1"
#8820000
0!
0"
#8830000
1!
1"
#8840000
0!
0"
#8880000
1!
1"
#8890000
0!
0"
#8910000
1!
1"
#8920000
0!
0"
#8930000
1!
1"
#8940000
0!
0"
#8960000
1!
1"
#8980000
0!
0"
#9000000
1!
1"
#9020000
0!
0"
#9030000
1!
1"
#9070000
0!
0"
#9080000
1!
1"
#9090000
0!
0"
#9110000
1!
1"
#9130000
0!
0"
#9140000
1!
1"
#9160000
0!
0"
#9170000
1!
1"
#9200000
0!
0"
#9210000
1!
1"
#9220000
0!
0"
#9230000
1!
1"
#9240000
0!
0"
#9330000
1!
1"
#9360000
0!
0"
#9390000
1!
1"
#9410000
0!
0"
#9420000
1!
1"
#9450000
0!
0"
#9470000
1!
1"
#9490000
0!
0"
#9530000
1!
1"
#9540000
0!
0"
#9550000
1!
1"
#9570000
0!
0"
#9580000
1!
1"
#9590000
0!
0"
#9600000
1!
1"
#9620000
0!
0"
#9630000
1!
1"
#9670000
0!
0"
#9680000
1!
1"
#9690000
0!
0"
#9700000
1!
1"
#9710000
0!
0"
#9750000
1!
1"
#9760000
0!
0"
#9770000
1!
1"
#9780000
0!
0"
#9800000
1!
1"
#9840000
0!
0"
#9850000
1!
1"
#9880000
0!
0"
#9900000
1!
1"
#9930000
0!
0"
#9940000
1!
1"
#9960000
0!
0"
#9980000
1!
1"
#9990000
0!
0"
